blackspammerbd_webdev/__init__.py
blackspammerbd_webdev/__main__.py
blackspammerbd_webdev/config.py
blackspammerbd_webdev/core.py
blackspammerbd_webdev/crawler.py
blackspammerbd_webdev/logger.py
blackspammerbd_webdev/reporter.py
blackspammerbd_webdev/utils.py
blackspammerbd_webdev/payloads/admin_paths.txt
blackspammerbd_webdev/payloads/load_payloads.py
blackspammerbd_webdev/payloads/passwords.txt
blackspammerbd_webdev/payloads/sql_payloads.txt
blackspammerbd_webdev/payloads/user_agents.txt
blackspammerbd_webdev/payloads/usernames.txt
blackspammerbd_webdev-1.0.0.dist-info/licenses/LICENSE
blackspammerbd_webdev-1.0.0.dist-info/METADATA
blackspammerbd_webdev-1.0.0.dist-info/WHEEL
blackspammerbd_webdev-1.0.0.dist-info/entry_points.txt
blackspammerbd_webdev-1.0.0.dist-info/top_level.txt
blackspammerbd_webdev-1.0.0.dist-info/RECORD
