Metadata-Version: 2.4
Name: blackspammerbd-webdev
Version: 1.0.0
Summary: The world’s most powerful, efficient, and professional web-pentester (2025), with dynamic payload loading and AJAX-aware crawling.
Home-page: https://github.com/BlackSpammerBd/blackspammerbd-webdev
Author: BLACK SPAMMER BD
Author-email: shawponsp6@gmail.com
License: MIT
Project-URL: Bug Tracker, https://github.com/BlackSpammerBd/blackspammerbd-webdev/issues
Project-URL: Documentation, https://github.com/BlackSpammerBd/blackspammerbd-webdev/wiki
Project-URL: Source Code, https://github.com/BlackSpammerBd/blackspammerbd-webdev
Project-URL: Author's Facebook, https://www.facebook.com/original.Typeboss.ur.father
Keywords: blackspammerbd web pentest ethical hacking cybersecurity cli tool
Classifier: Development Status :: 5 - Production/Stable
Classifier: Intended Audience :: Developers
Classifier: Intended Audience :: Information Technology
Classifier: Topic :: Security :: Cryptography
Classifier: Topic :: Software Development :: Build Tools
Classifier: License :: OSI Approved :: MIT License
Classifier: Programming Language :: Python :: 3
Classifier: Programming Language :: Python :: 3.8
Classifier: Operating System :: OS Independent
Requires-Python: >=3.8
License-File: LICENSE
Requires-Dist: click>=8.0
Requires-Dist: requests>=2.25
Requires-Dist: beautifulsoup4>=4.9
Requires-Dist: tqdm>=4.64
Requires-Dist: PyYAML>=6.0
Requires-Dist: colorama>=0.4
Dynamic: author
Dynamic: author-email
Dynamic: classifier
Dynamic: description
Dynamic: description-content-type
Dynamic: home-page
Dynamic: keywords
Dynamic: license
Dynamic: license-file
Dynamic: project-url
Dynamic: requires-dist
Dynamic: requires-python
Dynamic: summary
